[
  {
    "filename": "weightloss",
    "title": "အဆီချ၊ ဝိတ်ချ လိုသူများအတွက် Program",
    "description": "အဆီချ၊ ဝိတ်ချ လိုသူများအတွက် အထူးစီစဥ်ရေးဆွဲထားပေးပါတယ်။ ...",
    "coverImage": "https://raw.githubusercontent.com/ufcmm/images/main/gympngs/kawaii-flat-icons/kflat-04.png"
  },
  {
    "filename": "weightloss",
    "title": "အဆီချ၊ ဝိတ်ချ လိုသူများအတွက် Program",
    "description": "အဆီချ၊ ဝိတ်ချ လိုသူများအတွက် အထူးစီစဥ်ရေးဆွဲထားပေးပါတယ်။ ...",
    "coverImage": "https://raw.githubusercontent.com/ufcmm/images/main/gympngs/kawaii-flat-icons/kflat-04.png"
  }
]
